{
  "name": "Gary Elliott",
  "age": 60,
  "address": {
    "street": "Urcap Terrace",
    "city": "Mirucra",
    "state": "NM",
    "zip": "07380"
  },
  "contact": {
    "phone": "(553) 702-6830",
    "servicePhone": "800515133"
  },
  "birthday": "1980-10-19T06:21:00.779Z",
  "ip": "97.138.232.243",
  "foo": "bar",
  "profile": {
    "about": "Ratananu dafe de rekiw igeec bakjemwu teji vepkij ojwapmo vujmomo kekil gic litad ne. Za vodnohit zuhih ciki jed ihecateb so uzacu ido loszohto bek deah di zosneczu kiwif rupugri sitez jinek. Zef vur feznu nu kobecze sosihid zopcel tewkidzi hafosita otu begew keuca saefduc cifta itiut tenaupu.",
    "bio": "Fupoh uruto helva za movu dobkis wi faw hihe uzimi vise raretoma ajozelfo. Enu tatca warcehbu ho setsovoz kiemo fagdiwev cim edmo pam kihpe ka oh ji imwele coez sawees bozfum. Fil dirtad awinoko cez sel zofo igo kecud coha ehebulhat dawwa al la jeupeze povresle fappenma opni okewo. Nogavuv ziaw rod pal dej haru ke rov eh ran wen divga rodbifti hadru diwuwi nif jef ej."
  },
  "apiKey": "93491f43144b7d39ef2fee1d768d5463a5b0065389a125dd4b78df96e9e6161b",
  "currency": {
    "code": "CDF",
    "name": "Congo/Kinshasa Franc"
  }
}